.gitattributes
.gitignore
LICENSE
MANIFEST.in
Makefile
README.md
conda_deps.txt
converter.py
pyproject.toml
.github/workflows/long_tests.yml
.github/workflows/publish.yml
.github/workflows/test.yml
.github/workflows/workflow.yml
acellera_atm.egg-info/PKG-INFO
acellera_atm.egg-info/SOURCES.txt
acellera_atm.egg-info/dependency_links.txt
acellera_atm.egg-info/entry_points.txt
acellera_atm.egg-info/top_level.txt
atm/__init__.py
atm/atom_nnp_wrapper.py
atm/atomutils.py
atm/logging.ini
atm/ommreplica.py
atm/ommsystem.py
atm/rbfe_production.py
atm/rbfe_structprep.py
atm/utils.py
atm/uwham.py
atm/worker.py
docs/Makefile
docs/getversion.py
docs/make.bat
docs/source/.gitignore
docs/source/app_atm.rst
docs/source/conf.py
docs/source/index.rst
docs/source/installation.rst
docs/source/modules.rst
docs/source/tutorial.rst
package/atm/.gitignore
package/atm/build.sh
package/atm/insert_placeholder_values.py
package/atm/recipe_template.yaml
tests/test_atm.py
tests/QB_A08_A07/QB_A08_A07.inpcrd
tests/QB_A08_A07/QB_A08_A07.prmtop
tests/QB_A08_A07/QB_A08_A07_asyncre.yaml
tests/QB_A08_A07/nodefile
tests/QB_A08_A07_completed/QB_A08_A07.inpcrd
tests/QB_A08_A07_completed/QB_A08_A07.prmtop
tests/QB_A08_A07_completed/QB_A08_A07_0.pdb
tests/QB_A08_A07_completed/QB_A08_A07_0.xml
tests/QB_A08_A07_completed/QB_A08_A07_asyncre.yaml
tests/QB_A08_A07_completed/QB_A08_A07_equil.pdb
tests/QB_A08_A07_completed/QB_A08_A07_equil.xml
tests/QB_A08_A07_completed/QB_A08_A07_mdlambda.out
tests/QB_A08_A07_completed/QB_A08_A07_mdlambda.pdb
tests/QB_A08_A07_completed/QB_A08_A07_mdlambda.xml
tests/QB_A08_A07_completed/QB_A08_A07_min.pdb
tests/QB_A08_A07_completed/QB_A08_A07_min.xml
tests/QB_A08_A07_completed/QB_A08_A07_npt.pdb
tests/QB_A08_A07_completed/QB_A08_A07_npt.xml
tests/QB_A08_A07_completed/QB_A08_A07_therm.pdb
tests/QB_A08_A07_completed/QB_A08_A07_therm.xml
tests/QB_A08_A07_completed/analyze.sh
tests/QB_A08_A07_completed/nodefile
tests/TYK2_A02_A09/TYK2_A02_A09_r0_1/r0/QB_A02_A09.out
tests/TYK2_A02_A09/TYK2_A02_A09_r0_1/r1/QB_A02_A09.out
tests/TYK2_A02_A09/TYK2_A02_A09_r0_1/r10/QB_A02_A09.out
tests/TYK2_A02_A09/TYK2_A02_A09_r0_1/r11/QB_A02_A09.out
