Metadata-Version: 2.2
Name: acellera-atm
Version: 0.0.18
Summary: A molecule reading/writing and manipulation package.
Author-email: Acellera <info@acellera.com>
Project-URL: Homepage, https://github.com/Acellera/atm
Project-URL: Bug Tracker, https://github.com/Acellera/atm/issues
Classifier: Programming Language :: Python :: 3
Classifier: Operating System :: POSIX :: Linux
Requires-Python: >=3.8
License-File: LICENSE
